packageurl/__init__.py
packageurl/py.typed
packageurl/utils.py
packageurl/contrib/__init__.py
packageurl/contrib/purl2url.py
packageurl/contrib/route.py
packageurl/contrib/url2purl.py
packageurl/contrib/django/__init__.py
packageurl/contrib/django/filters.py
packageurl/contrib/django/models.py
packageurl/contrib/django/utils.py
packageurl/contrib/sqlalchemy/mixin.py
packageurl_python-0.17.4.dist-info/METADATA
packageurl_python-0.17.4.dist-info/WHEEL
packageurl_python-0.17.4.dist-info/top_level.txt
packageurl_python-0.17.4.dist-info/RECORD
