Metadata-Version: 2.4
Name: packageurl-python
Version: 0.17.4
Summary: A purl aka. Package URL parser and builder
Home-page: https://github.com/package-url/packageurl-python
Author: the purl authors
License: MIT
Keywords: package,url,package manager,package url
Classifier: Development Status :: 4 - Beta
Classifier: Intended Audience :: Developers
Classifier: License :: OSI Approved :: MIT License
Classifier: Operating System :: OS Independent
Classifier: Programming Language :: Python
Classifier: Programming Language :: Python :: 3 :: Only
Classifier: Programming Language :: Python :: 3.8
Classifier: Programming Language :: Python :: 3.9
Classifier: Programming Language :: Python :: 3.10
Classifier: Programming Language :: Python :: 3.11
Classifier: Programming Language :: Python :: 3.12
Classifier: Programming Language :: Python :: 3.13
Classifier: Topic :: Software Development :: Libraries
Classifier: Topic :: Utilities
Classifier: Typing :: Typed
Requires-Python: >=3.8
Provides-Extra: lint
Requires-Dist: isort; extra == "lint"
Requires-Dist: black; extra == "lint"
Requires-Dist: mypy; extra == "lint"
Provides-Extra: test
Requires-Dist: pytest; extra == "test"
Provides-Extra: build
Requires-Dist: setuptools; extra == "build"
Requires-Dist: wheel; extra == "build"
Provides-Extra: sqlalchemy
Requires-Dist: sqlalchemy>=2.0.0; extra == "sqlalchemy"
